{
    "AX": {
        "error": 0.009427957371440074,
        "error_type": "SEM",
        "filter_outliers_dict": {
            "filter_outliers": true,
            "iterations": 1,
            "std_devs": 3,
            "use_iqr_filtering": false,
            "use_standard_deviation_filtering": false
        },
        "fit": "average",
        "fn": 40,
        "include_baseline_error": false,
        "n": 40,
        "outlier_excluded": [],
        "reviewed": true,
        "user_excluded": [],
        "value": -0.14244076265313196
    },
    "CDD": {
        "error": 2.2670584560103537e-05,
        "error_type": "SEM",
        "filter_outliers_dict": {
            "filter_outliers": true,
            "iterations": 1,
            "std_devs": 10,
            "use_iqr_filtering": false,
            "use_standard_deviation_filtering": false
        },
        "fit": "average",
        "fn": 40,
        "include_baseline_error": false,
        "n": 40,
        "outlier_excluded": [],
        "reviewed": true,
        "user_excluded": [],
        "value": 0.00010686705099942629
    },
    "H1": {
        "error": 0.007652335126282417,
        "error_type": "SEM",
        "filter_outliers_dict": {
            "filter_outliers": true,
            "iterations": 1,
            "std_devs": 3,
            "use_iqr_filtering": false,
            "use_standard_deviation_filtering": false
        },
        "fit": "average",
        "fn": 40,
        "include_baseline_error": false,
        "n": 40,
        "outlier_excluded": [],
        "reviewed": true,
        "user_excluded": [],
        "value": 0.023764508310705423
    },
    "H2": {
        "error": 0.002998563043502398,
        "error_type": "SEM",
        "filter_outliers_dict": {
            "filter_outliers": true,
            "iterations": 1,
            "std_devs": 3,
            "use_iqr_filtering": false,
            "use_standard_deviation_filtering": false
        },
        "fit": "average",
        "fn": 40,
        "include_baseline_error": false,
        "n": 40,
        "outlier_excluded": [],
        "reviewed": true,
        "user_excluded": [],
        "value": -0.024167566674077535
    },
    "L1": {
        "error": 0.003446250509514662,
        "error_type": "SEM",
        "filter_outliers_dict": {
            "filter_outliers": true,
            "iterations": 1,
            "std_devs": 3,
            "use_iqr_filtering": false,
            "use_standard_deviation_filtering": false
        },
        "fit": "average",
        "fn": 40,
        "include_baseline_error": false,
        "n": 40,
        "outlier_excluded": [],
        "reviewed": true,
        "user_excluded": [],
        "value": 0.0657731912098825
    },
    "L2": {
        "error": 0.00771177167711682,
        "error_type": "SEM",
        "filter_outliers_dict": {
            "filter_outliers": true,
            "iterations": 1,
            "std_devs": 2
        },
        "fit": "average",
        "value": -0.07694613225951764
    }
}