{
    "AX": {
        "error": 0.009535101069099551,
        "error_type": "SEM",
        "filter_outliers_dict": {
            "filter_outliers": true,
            "iterations": 1,
            "std_devs": 3,
            "use_iqr_filtering": false,
            "use_standard_deviation_filtering": false
        },
        "fit": "average",
        "fn": 40,
        "include_baseline_error": false,
        "n": 40,
        "outlier_excluded": [],
        "reviewed": true,
        "user_excluded": [],
        "value": -0.14612080692313612
    },
    "CDD": {
        "error": 9.778527593063318e-06,
        "error_type": "SEM",
        "filter_outliers_dict": {
            "filter_outliers": true,
            "iterations": 1,
            "std_devs": 10,
            "use_iqr_filtering": false,
            "use_standard_deviation_filtering": false
        },
        "fit": "average",
        "fn": 40,
        "include_baseline_error": false,
        "n": 40,
        "outlier_excluded": [],
        "reviewed": true,
        "user_excluded": [],
        "value": 3.053344262298197e-05
    },
    "H1": {
        "error": 0.006774474804801137,
        "error_type": "SEM",
        "filter_outliers_dict": {
            "filter_outliers": true,
            "iterations": 1,
            "std_devs": 3,
            "use_iqr_filtering": false,
            "use_standard_deviation_filtering": false
        },
        "fit": "average",
        "fn": 40,
        "include_baseline_error": false,
        "n": 40,
        "outlier_excluded": [],
        "reviewed": true,
        "user_excluded": [],
        "value": 0.010930679005105049
    },
    "H2": {
        "error": 0.002660688519663878,
        "error_type": "SEM",
        "filter_outliers_dict": {
            "filter_outliers": true,
            "iterations": 1,
            "std_devs": 3,
            "use_iqr_filtering": false,
            "use_standard_deviation_filtering": false
        },
        "fit": "average",
        "fn": 40,
        "include_baseline_error": false,
        "n": 40,
        "outlier_excluded": [],
        "reviewed": true,
        "user_excluded": [],
        "value": -0.018720439178378002
    },
    "L1": {
        "error": 0.003228848493941979,
        "error_type": "SEM",
        "filter_outliers_dict": {
            "filter_outliers": true,
            "iterations": 1,
            "std_devs": 3,
            "use_iqr_filtering": false,
            "use_standard_deviation_filtering": false
        },
        "fit": "average",
        "fn": 40,
        "include_baseline_error": false,
        "n": 40,
        "outlier_excluded": [],
        "reviewed": true,
        "user_excluded": [],
        "value": 0.061586280970368536
    },
    "L2": {
        "error": 0.005847303111845129,
        "error_type": "SEM",
        "filter_outliers_dict": {
            "filter_outliers": true,
            "iterations": 1,
            "std_devs": 2
        },
        "fit": "average",
        "value": -0.06673197800060846
    }
}